[
  {
    "date": "2025-07-14T19:25:18.633Z",
    "items": [
      {
        "id": "cart_1752521055186-0.09776767299452749",
        "partId": "1752521055186-0.09776767299452749",
        "name": "IMPRESSORA HP P1102 SEMI NOVA ",
        "quantity": 1,
        "unitPrice": 400,
        "totalPrice": 400
      }
    ],
    "subtotal": 400,
    "discount": 0,
    "total": 400,
    "paymentMethod": "Dinheiro",
    "status": "Finalizada",
    "userId": "1752520921537-0.9328935433699823",
    "userName": "Wagner Lopes",
    "notes": "",
    "id": "1752521118633-0.5933779120052836",
    "time": "16:25:18",
    "user": "Não identificado"
  },
  {
    "date": "2025-07-16T18:52:52.780Z",
    "items": [
      {
        "id": "cart_1752690773908-0.9374151604165823",
        "partId": "1752690773908-0.9374151604165823",
        "name": "TAMPA SCANNER  M1132",
        "quantity": 1,
        "unitPrice": 100,
        "totalPrice": 100
      }
    ],
    "subtotal": 100,
    "discount": 0,
    "total": 100,
    "paymentMethod": "Dinheiro",
    "status": "Finalizada",
    "userId": "1752520921537-0.9328935433699823",
    "userName": "Wagner Lopes",
    "notes": "",
    "id": "1752691972781-0.45823819003991484",
    "time": "15:52:52",
    "user": "Não identificado"
  },
  {
    "date": "2025-07-22T21:23:26.554Z",
    "items": [
      {
        "id": "cart_1753219402225_0.5177903660498016",
        "partId": "1753219157792-0.45614006171448906",
        "name": "ADAPTADOR WIFI PR-802 150 MBPS",
        "quantity": 1,
        "unitPrice": 65,
        "totalPrice": 65
      }
    ],
    "subtotal": 65,
    "discount": 0,
    "total": 65,
    "paymentMethod": "Cartão de Crédito",
    "status": "Finalizada",
    "userId": "1752520921537-0.9328935433699823",
    "userName": "Wagner Lopes",
    "notes": "",
    "id": "1753219406554-0.4903733147074246",
    "time": "18:23:26",
    "user": "Não identificado"
  },
  {
    "id": "SALE-1753635103143",
    "date": "2025-07-27",
    "time": "13:51:57",
    "user": "Wagner Lopes",
    "items": [
      {
        "id": "PROD-1753146048116",
        "barcode": "PROD-1753146048116",
        "name": "teste 7",
        "price": 20,
        "quantity": 3,
        "category": "peças",
        "description": "uygjhgjh",
        "unitOfMeasure": "UN",
        "costPrice": 15,
        "minStock": 2
      }
    ],
    "subtotal": 60,
    "discount": 0,
    "total": 60,
    "paymentMethod": "dinheiro",
    "observations": ""
  },
  {
    "id": "SALE-1753909134949",
    "date": "2025-07-30",
    "time": "17:58:57",
    "user": "Wagner Lopes",
    "items": [
      {
        "name": "xerox",
        "price": 50,
        "quantity": 1,
        "id": "manual-1753909129749"
      }
    ],
    "subtotal": 50,
    "discount": 0,
    "total": 50,
    "paymentMethod": "pix",
    "observations": ""
  },
  {
    "id": "SALE-1753909292876",
    "date": "2025-07-30",
    "time": "18:01:59",
    "user": "Wagner Lopes",
    "items": [
      {
        "name": "xerox",
        "price": 10,
        "quantity": 1,
        "id": "manual-1753909249061"
      }
    ],
    "subtotal": 10,
    "discount": 0,
    "total": 10,
    "paymentMethod": "pix",
    "observations": ""
  },
  {
    "id": "SALE-1754250804462",
    "date": "2025-08-03",
    "time": "16:53:24",
    "user": "Wagner Lopes",
    "items": [
      {
        "name": "teste",
        "price": 10,
        "quantity": 1,
        "id": "manual-1754250789276"
      }
    ],
    "subtotal": 10,
    "discount": 0,
    "total": 10,
    "paymentMethod": "credito",
    "observations": "teste "
  }
]